havc/__init__.py
havc/app.py
havc/arguments.py
havc/command.py
havc/output.py
havc/progsettings.yaml
havc/search.py
havc/configurations/__init__.py
havc/configurations/configurations.py
havc/entities/__init__.py
havc/entities/argument.py
havc/entities/prog_arguments.py
havc/entities/video_file.py
havc/services/__init__.py
havc/services/directory.py
havc/services/file.py
havc/utils/__init__.py
havc/utils/bytes_conversion.py
havc/utils/error.py
havc/utils/operating_system.py
havc/utils/progsettings.py
havc/utils/split_string.py
havc-1.4.0.dist-info/LICENSE
havc-1.4.0.dist-info/METADATA
havc-1.4.0.dist-info/WHEEL
havc-1.4.0.dist-info/entry_points.txt
havc-1.4.0.dist-info/top_level.txt
havc-1.4.0.dist-info/RECORD
