Metadata-Version: 2.1
Name: havc
Version: 1.4.0
Summary: An automatic video converter using HandBrake CLI.
Home-page: https://github.com/zaytiri/handbrake-automatic-video-converter
Author: zaytiri
Project-URL: GitHub, https://github.com/zaytiri/handbrake-automatic-video-converter
Project-URL: Changelog, https://github.com/zaytiri/handbrake-automatic-video-converter/blob/main/CHANGELOG.md
Keywords: handbrake,cli,console,video,converter,encoder
Classifier: Environment :: Console
Classifier: Intended Audience :: Developers
Classifier: License :: OSI Approved :: MIT License
Classifier: Operating System :: OS Independent
Classifier: Programming Language :: Python :: 3
Requires-Python: >=3.10.6
License-File: LICENSE
Requires-Dist: PyYAML~=6.0
